{
  "todos1": [
    {
      "id": 1,
      "title": "할일1",
      "contents": "리액트",
      "isDone": false
    },
    {
      "id": 2,
      "title": "할일2",
      "contents": "스프링",
      "isDone": false
    },
    {
      "id": 3,
      "title": "할일3",
      "contents": "운동",
      "isDone": false
    },
    {
      "title": "123",
      "contents": "123",
      "isDone": false,
      "id": "6c04ac84-d9a6-4a61-b2c9-bd28562c311b"
    },
    {
      "title": "123",
      "contents": "123",
      "isDone": false,
      "id": "2d2fb765-9dab-437e-956d-4cc1d50e8812"
    },
    {
      "title": "123",
      "contents": "123",
      "isDone": false,
      "id": "74635f39-209b-43c4-b4f9-4589206d88ad"
    },
    {
      "title": "123",
      "contents": "123",
      "isDone": false,
      "id": "7a2bffdf-4e7b-4387-8c39-984fb3025cc2"
    }
  ]
}